Assignment_3/3-bit_counter.v
module counter_7_to_0 (
    input wire clk,
    input wire reset,
    output reg [2:0] count
);

    always @(posedge clk or posedge reset) begin
        if (reset)
            count <= 3'b111;   // Reset to 7
        else
            count <= count - 1; // Count down
    end
endmodule

module tb_counter_7_to_0;

    reg clk, reset;
    wire [2:0] count;

    counter_7_to_0 uut (
        .clk(clk),
        .reset(reset),
        .count(count)
    );

    initial begin
        clk = 0;
        forever #5 clk = ~clk; // Clock period of 10ns
    end

    initial begin
        // $monitor("Time = %0dns, Count = %d", $time, count);
        $dumpfile("3-bit_counter.vcd");
        $dumpvars(0, tb_counter_7_to_0);
        reset = 1; #10 reset = 0; // Start with reset active

        // Let the counter count down from 7 to 0
        $finish;
    end
endmodule

Assignment_3/3-bit_counter.vcd
$date
	Fri Sep 27 23:21:28 2024
$end
$version
	Icarus Verilog
$end
$timescale
	1s
$end
$scope module tb_counter_7_to_0 $end
$var wire 3 ! count [2:0] $end
$var reg 1 " clk $end
$var reg 1 # reset $end
$scope module uut $end
$var wire 1 " clk $end
$var wire 1 # reset $end
$var reg 3 $ count [2:0] $end
$upscope $end
$upscope $end
$enddefinitions $end
#0
$dumpvars
b111 $
1#
0"
b111 !
$end
#5
1"
#10
0"
0#
#15
b110 !
b110 $
1"
#20
0"
#25
b101 !
b101 $
1"
#30
0"
#35
b100 !
b100 $
1"
#40
0"
#45
b11 !
b11 $
1"
#50
0"
#55
b10 !
b10 $
1"
#60
0"
#65
b1 !
b1 $
1"
#70
0"
#75
b0 !
b0 $
1"
#80
0"
#85
b111 !
b111 $
1"
