Assignment_3/graycode_counter.v
module gray_code_counter (
    input wire clk,
    input wire reset,
    input wire up,      // 1 for UP, 0 for DOWN
    output reg [2:0] gray_code
);

    reg [2:0] binary;

    // Binary to Gray code conversion
    always @(posedge clk or posedge reset) begin
        if (reset) begin
            binary <= 3'b000;
        end
        else if (up) begin
            binary <= binary + 1;
        end
        else begin
            binary <= binary - 1;
        end
    end

    always @(*) begin
        gray_code = (binary >> 1) ^ binary;  // Convert binary to gray code i.e. g[i] = b[i] ^ b[i+1]
    end
endmodule

module tb_gray_code_counter;

    reg clk, reset, up;
    wire [2:0] gray_code;

    gray_code_counter uut (
        .clk(clk),
        .reset(reset),
        .up(up),
        .gray_code(gray_code)
    );

    initial begin
        clk = 0;
        forever #5 clk = ~clk; // Clock period of 10ns
    end

    initial begin
        // $monitor("Time = %0dns, Gray Code = %b", $time, gray_code);
        $dumpfile("graycode_counter.vcd");
        $dumpvars(0, tb_gray_code_counter);
        reset = 1; up = 1; #10 reset = 0;

        // Count up
        #50 up = 0;

        // Count down
        #50 $finish;
    end
endmodule

Assignment_3/graycode_counter.vcd
$date
	Sat Sep 28 00:18:41 2024
$end
$version
	Icarus Verilog
$end
$timescale
	1s
$end
$scope module tb_gray_code_counter $end
$var wire 3 ! gray_code [2:0] $end
$var reg 1 " clk $end
$var reg 1 # reset $end
$var reg 1 $ up $end
$scope module uut $end
$var wire 1 " clk $end
$var wire 1 # reset $end
$var wire 1 $ up $end
$var reg 3 % binary [2:0] $end
$var reg 3 & gray_code [2:0] $end
$upscope $end
$upscope $end
$enddefinitions $end
#0
$dumpvars
b0 &
b0 %
1$
1#
0"
b0 !
$end
#5
1"
#10
0"
0#
#15
b1 !
b1 &
b1 %
1"
#20
0"
#25
b11 !
b11 &
b10 %
1"
#30
0"
#35
b10 !
b10 &
b11 %
1"
#40
0"
#45
b110 !
b110 &
b100 %
1"
#50
0"
#55
b111 !
b111 &
b101 %
1"
#60
0"
0$
#65
b110 !
b110 &
b100 %
1"
#70
0"
#75
b10 !
b10 &
b11 %
1"
#80
0"
#85
b11 !
b11 &
b10 %
1"
#90
0"
#95
b1 !
b1 &
b1 %
1"
#100
0"
#105
b0 !
b0 &
b0 %
1"
