Assignment_3/nbit_shift_register.v
module shift_register #(parameter N = 8) (
    input wire clk,
    input wire reset,
    input wire shift_dir,  // 1 for right, 0 for left
    input wire [N-1:0] data_in,
    output reg [N-1:0] data_out
);
   

    always @(posedge clk or posedge reset) begin
        if (reset)
            data_out <= data_in;
        else if (shift_dir)
            data_out <= data_out >> 1; // Shift right
        else
            data_out <= data_out << 1; // Shift left
    end
endmodule

module tb_shift_register;

    reg clk, reset, shift_dir;
    reg [7:0] data_in;
    wire [7:0] data_out;

    shift_register #(8) uut (
        .clk(clk),
        .reset(reset),
        .shift_dir(shift_dir),
        .data_in(data_in),
        .data_out(data_out)
    );

    initial begin
        clk = 0;
        forever #5 clk = ~clk;
    end

    initial begin
        $dumpfile("nbit_shift_register.vcd");
        $dumpvars(0, tb_shift_register);

        reset = 1; data_in = 8'b10101010; shift_dir = 1; #10 reset = 0;

        // Shift right
        #50 shift_dir = 0;

        // Shift left
        #50 $finish;
    end
endmodule

Assignment_3/nbit_shift_register.vcd
$date
	Sat Sep 28 00:59:23 2024
$end
$version
	Icarus Verilog
$end
$timescale
	1s
$end
$scope module tb_shift_register $end
$var wire 8 ! data_out [7:0] $end
$var reg 1 " clk $end
$var reg 8 # data_in [7:0] $end
$var reg 1 $ reset $end
$var reg 1 % shift_dir $end
$scope module uut $end
$var wire 1 " clk $end
$var wire 8 & data_in [7:0] $end
$var wire 1 $ reset $end
$var wire 1 % shift_dir $end
$var reg 8 ' data_out [7:0] $end
$upscope $end
$upscope $end
$enddefinitions $end
#0
$dumpvars
b10101010 '
b10101010 &
1%
1$
b10101010 #
0"
b10101010 !
$end
#5
1"
#10
0"
0$
#15
b1010101 !
b1010101 '
1"
#20
0"
#25
b101010 !
b101010 '
1"
#30
0"
#35
b10101 !
b10101 '
1"
#40
0"
#45
b1010 !
b1010 '
1"
#50
0"
#55
b101 !
b101 '
1"
#60
0"
0%
#65
b1010 !
b1010 '
1"
#70
0"
#75
b10100 !
b10100 '
1"
#80
0"
#85
b101000 !
b101000 '
1"
#90
0"
#95
b1010000 !
b1010000 '
1"
#100
0"
#105
b10100000 !
b10100000 '
1"
